pkg/__init__.py
rikaard_dep2_depends_rikaard_dep1-0.0.7.dist-info/LICENSE
rikaard_dep2_depends_rikaard_dep1-0.0.7.dist-info/METADATA
rikaard_dep2_depends_rikaard_dep1-0.0.7.dist-info/WHEEL
rikaard_dep2_depends_rikaard_dep1-0.0.7.dist-info/top_level.txt
rikaard_dep2_depends_rikaard_dep1-0.0.7.dist-info/RECORD
