Metadata-Version: 2.1
Name: rikaard-dep2-depends-rikaard-dep1
Version: 0.0.7
Summary: A small example package
Home-page: https://github.com/pypa/sampleproject
Author: Rikaard Hosein
Author-email: rikaard.hosein@gmail.com
License: UNKNOWN
Project-URL: Bug Tracker, https://github.com/pypa/sampleproject/issues
Platform: UNKNOWN
Classifier: Programming Language :: Python :: 3
Classifier: License :: OSI Approved :: MIT License
Classifier: Operating System :: OS Independent
Requires-Python: >=3.6
Requires-Dist: rikaard-dep1
